[
  {
    "@type": "Organization",
    "actor_id": "bulk-infrastructure",
    "actor_name": "Bulk Infrastructure",
    "actor_type": "infrastructure_operator",
    "country_id": "NO",
    "website": "https://bulkinfrastructure.com"
  },
  {
    "@type": "Organization",
    "actor_id": "space-norway",
    "actor_name": "Space Norway",
    "actor_type": "state_owned_enterprise",
    "country_id": "NO",
    "website": "https://spacenorway.com"
  },
  {
    "@type": "Organization",
    "actor_id": "tampnet",
    "actor_name": "Tampnet",
    "actor_type": "network_operator",
    "country_id": "NO",
    "website": "https://www.tampnet.com"
  },
  {
    "@type": "Organization",
    "actor_id": "altibox-carrier",
    "actor_name": "Altibox Carrier",
    "actor_type": "telecom_operator",
    "country_id": "NO",
    "website": "https://www.submarinenetworks.com/en/systems/intra-europe/no-uk"
  },
  {
    "@type": "Organization",
    "actor_id": "lyse-altibox",
    "actor_name": "Lyse/Altibox",
    "actor_type": "telecom_operator",
    "country_id": "NO",
    "website": "https://www.submarinenetworks.com/en/systems/intra-europe/skagen-fiber-west"
  },
  {
    "@type": "Organization",
    "actor_id": "greenmountain",
    "actor_name": "Green Mountain",
    "actor_type": "datacenter_operator",
    "country_id": "NO",
    "website": "https://greenmountain.no"
  },
  {
    "@type": "Organization",
    "actor_id": "n0r5ke-fibre",
    "actor_name": "N0r5ke Fibre",
    "actor_type": "infrastructure_operator",
    "country_id": "NO",
    "website": "https://www.submarinenetworks.com/en/systems/intra-europe/n0r5ke-viking"
  },
  {
    "@type": "Organization",
    "actor_id": "ioema-fibre",
    "actor_name": "IOEMA Fibre Ltd",
    "actor_type": "project_company",
    "country_id": "GB",
    "website": "https://www.submarinenetworks.com/en/systems/intra-europe/ioema"
  },
  {
    "@type": "Organization",
    "actor_id": "celtic-norse",
    "actor_name": "Celtic Norse AS",
    "actor_type": "project_company",
    "country_id": "NO",
    "website": "https://www.submarinenetworks.com/en/systems/intra-europe/celtic-norse"
  },
  {
    "@type": "Organization",
    "actor_id": "aqua-comms",
    "actor_name": "Aqua Comms",
    "actor_type": "subsea_operator",
    "country_id": "IE",
    "website": "https://www.aquacomms.com"
  },
  {
    "@type": "Organization",
    "actor_id": "meta",
    "actor_name": "Meta",
    "actor_type": "tech_company",
    "country_id": "US",
    "notes": "US company; generally subject to US law."
  },
  {
    "@type": "Organization",
    "actor_id": "google",
    "actor_name": "Google",
    "actor_type": "tech_company",
    "country_id": "US",
    "notes": "US company; generally subject to US law."
  },
  {
    "@type": "Organization",
    "actor_id": "vodafone-iceland",
    "actor_name": "Vodafone Iceland",
    "actor_type": "telecom_operator",
    "country_id": "IS"
  },
  {
    "@type": "Organization",
    "actor_id": "no-uk-com",
    "actor_name": "NO-UK Com (consortium)",
    "actor_type": "consortium",
    "country_id": "NO",
    "website": "https://www.submarinenetworks.com/en/systems/intra-europe/no-uk"
  },
  {
    "@type": "Organization",
    "actor_id": "subcom",
    "actor_name": "SubCom",
    "actor_type": "system_supplier",
    "country_id": "US",
    "website": "https://www.subcom.com",
    "notes": "System supplier referenced for Arctic Way."
  },
  {
    "@type": "Organization",
    "actor_id": "nexans",
    "actor_name": "Nexans",
    "actor_type": "cable_manufacturer",
    "country_id": "FR",
    "website": "https://www.nexans.com",
    "notes": "Cable manufacturer referenced for NORFEST."
  },
  {
    "@type": "Organization",
    "actor_id": "cecon-contracting",
    "actor_name": "Cecon Contracting AS",
    "actor_type": "installation_contractor",
    "country_id": "NO",
    "website": "https://www.cecon.no",
    "notes": "Installation contractor referenced for NORFEST."
  }
]
